avtomatika/__init__.py
avtomatika/api.html
avtomatika/app_keys.py
avtomatika/blueprint.py
avtomatika/client_config_loader.py
avtomatika/compression.py
avtomatika/config.py
avtomatika/constants.py
avtomatika/context.py
avtomatika/data_types.py
avtomatika/datastore.py
avtomatika/dispatcher.py
avtomatika/engine.py
avtomatika/executor.py
avtomatika/health_checker.py
avtomatika/logging_config.py
avtomatika/metrics.py
avtomatika/py.typed
avtomatika/quota.py
avtomatika/ratelimit.py
avtomatika/reputation.py
avtomatika/s3.py
avtomatika/scheduler.py
avtomatika/scheduler_config_loader.py
avtomatika/security.py
avtomatika/telemetry.py
avtomatika/watcher.py
avtomatika/worker_config_loader.py
avtomatika/ws_manager.py
avtomatika/api/handlers.py
avtomatika/api/routes.py
avtomatika/history/base.py
avtomatika/history/noop.py
avtomatika/history/postgres.py
avtomatika/history/sqlite.py
avtomatika/storage/__init__.py
avtomatika/storage/base.py
avtomatika/storage/memory.py
avtomatika/storage/redis.py
avtomatika/utils/__init__.py
avtomatika/utils/webhook_sender.py
avtomatika-1.0b8.dist-info/licenses/LICENSE
avtomatika-1.0b8.dist-info/METADATA
avtomatika-1.0b8.dist-info/WHEEL
avtomatika-1.0b8.dist-info/top_level.txt
avtomatika-1.0b8.dist-info/RECORD
