Metadata-Version: 2.4
Name: avtomatika
Version: 1.0b8
Summary: A state-machine based orchestrator for long-running AI and other jobs.
Project-URL: Homepage, https://github.com/avtomatika-ai/avtomatika
Project-URL: Bug Tracker, https://github.com/avtomatika-ai/avtomatika/issues
Classifier: Development Status :: 4 - Beta
Classifier: Programming Language :: Python :: 3
Classifier: License :: OSI Approved :: MIT License
Classifier: Operating System :: OS Independent
Requires-Python: >=3.11
License-File: LICENSE
Requires-Dist: aiohttp~=3.12
Requires-Dist: python-json-logger~=4.0
Requires-Dist: graphviz~=0.21
Requires-Dist: zstandard~=0.24
Requires-Dist: aioprometheus~=23.12
Requires-Dist: msgpack~=1.1
Requires-Dist: orjson~=3.11
Provides-Extra: redis
Requires-Dist: redis~=7.1; extra == "redis"
Provides-Extra: s3
Requires-Dist: obstore>=0.2; extra == "s3"
Requires-Dist: aiofiles~=23.2; extra == "s3"
Provides-Extra: history
Requires-Dist: aiosqlite~=0.22; extra == "history"
Requires-Dist: asyncpg~=0.30; extra == "history"
Provides-Extra: telemetry
Requires-Dist: opentelemetry-api~=1.39; extra == "telemetry"
Requires-Dist: opentelemetry-sdk~=1.39; extra == "telemetry"
Requires-Dist: opentelemetry-exporter-otlp~=1.39; extra == "telemetry"
Requires-Dist: opentelemetry-instrumentation-aiohttp-client~=0.59b0; extra == "telemetry"
Provides-Extra: test
Requires-Dist: pytest~=9.0; extra == "test"
Requires-Dist: pytest-asyncio~=1.1; extra == "test"
Requires-Dist: fakeredis~=2.33; extra == "test"
Requires-Dist: pytest-aiohttp~=1.1; extra == "test"
Requires-Dist: pytest-mock~=3.14; extra == "test"
Requires-Dist: aioresponses~=0.7; extra == "test"
Requires-Dist: backports.zstd~=1.2; extra == "test"
Requires-Dist: opentelemetry-instrumentation-aiohttp-client; extra == "test"
Requires-Dist: obstore>=0.2; extra == "test"
Requires-Dist: aiofiles~=23.2; extra == "test"
Provides-Extra: all
Requires-Dist: avtomatika[redis]; extra == "all"
Requires-Dist: avtomatika[history]; extra == "all"
Requires-Dist: avtomatika[telemetry]; extra == "all"
Requires-Dist: avtomatika[s3]; extra == "all"
Dynamic: license-file
